coffee_maker/__init__.py
coffee_maker/ai_providers/__init__.py
coffee_maker/ai_providers/base.py
coffee_maker/ai_providers/fallback_strategy.py
coffee_maker/ai_providers/provider_config.py
coffee_maker/ai_providers/provider_factory.py
coffee_maker/ai_providers/providers/__init__.py
coffee_maker/ai_providers/providers/claude_provider.py
coffee_maker/ai_providers/providers/gemini_provider.py
coffee_maker/ai_providers/providers/openai_provider.py
coffee_maker/api/__init__.py
coffee_maker/api/main.py
coffee_maker/api/models/__init__.py
coffee_maker/api/routes/__init__.py
coffee_maker/api/routes/daemon.py
coffee_maker/api/routes/files.py
coffee_maker/api/routes/status.py
coffee_maker/auto_gemini_styleguide.py
coffee_maker/autonomous/README.md
coffee_maker/autonomous/__init__.py
coffee_maker/autonomous/ace/__init__.py
coffee_maker/autonomous/ace/api.py
coffee_maker/autonomous/ace/config.py
coffee_maker/autonomous/ace/file_ownership.py
coffee_maker/autonomous/ace/file_tools.py
coffee_maker/autonomous/ace/generator.py
coffee_maker/autonomous/ace/insights.py
coffee_maker/autonomous/ace/models.py
coffee_maker/autonomous/ace/playbook_loader.py
coffee_maker/autonomous/ace/trace_manager.py
coffee_maker/autonomous/activity_db.py
coffee_maker/autonomous/activity_logger.py
coffee_maker/autonomous/agent_registry.py
coffee_maker/autonomous/agent_skill_controller.py
coffee_maker/autonomous/agents/__init__.py
coffee_maker/autonomous/agents/architect_agent.py
coffee_maker/autonomous/agents/architect_skills_mixin.py
coffee_maker/autonomous/agents/assistant_agent.py
coffee_maker/autonomous/agents/base_agent.py
coffee_maker/autonomous/agents/code_developer_agent.py
coffee_maker/autonomous/agents/code_developer_commit_review_mixin.py
coffee_maker/autonomous/agents/code_searcher_agent.py
coffee_maker/autonomous/agents/project_manager_agent.py
coffee_maker/autonomous/agents/ux_design_expert_agent.py
coffee_maker/autonomous/architect_daily_routine.py
coffee_maker-0.1.5.dist-info/METADATA
coffee_maker-0.1.5.dist-info/WHEEL
coffee_maker-0.1.5.dist-info/entry_points.txt
coffee_maker-0.1.5.dist-info/RECORD
