Metadata-Version: 2.4
Name: coffee_maker
Version: 0.1.5
Summary: An agent that roast, grind, brew and serve your coffee. or not...
License: Apache 2.0
Author: Bobain and some code agents
Requires-Python: >=3.11,<3.14
Classifier: License :: Other/Proprietary License
Classifier: Programming Language :: Python :: 3
Classifier: Programming Language :: Python :: 3.11
Classifier: Programming Language :: Python :: 3.12
Classifier: Programming Language :: Python :: 3.13
Requires-Dist: Pygments (>=2.18.0,<3.0.0)
Requires-Dist: anthropic (>=0.40.0,<0.41.0)
Requires-Dist: gitpython (>=3.1.45,<4.0.0)
Requires-Dist: google (>=3.0.0,<4.0.0)
Requires-Dist: gradio[mcp] (>=5.31.0,<6.0.0)
Requires-Dist: langchain-core (>=0.3.78,<0.4.0)
Requires-Dist: langchain[anthropic,community,core,google-genai,openai] (>=0.3.27,<0.4.0)
Requires-Dist: langfuse[langchain] (>=3.5.2,<4.0.0)
Requires-Dist: llama-index (>=0.12.44,<0.13.0)
Requires-Dist: llama-index-llms-ollama (>=0.6.2,<0.7.0)
Requires-Dist: llama-index-tools-mcp (>=0.2.5,<0.3.0)
Requires-Dist: mcp[cli] (>=1.9.0,<2.0.0)
Requires-Dist: pandas (>=2.2.0,<3.0.0)
Requires-Dist: plotly (>=5.18.0,<6.0.0)
Requires-Dist: prompt-toolkit (>=3.0.47,<4.0.0)
Requires-Dist: psutil (>=7.0.0,<8.0.0)
Requires-Dist: pygithub (>=2.8.1,<3.0.0)
Requires-Dist: python-dotenv (>=1.1.0,<2.0.0)
Requires-Dist: pyyaml (>=6.0.3,<7.0.0)
Requires-Dist: streamlit (>=1.32.0,<2.0.0)
Project-URL: Bug Tracker, https://github.com/Bobain/MonolithicCoffeeMakerAgent/issues
Project-URL: Homepage, https://github.com/Bobain/MonolithicCoffeeMakerAgent
Project-URL: Repository, https://github.com/Bobain/MonolithicCoffeeMakerAgent
